cofog/__init__.py
cofog/__main__.py
cofog/cofog.py
cofog/data.py
cofog/exceptions.py
cofog/parser.py
cofog/py.typed
cofog/types.py
cofog-2.0.0.dist-info/entry_points.txt
cofog-2.0.0.dist-info/LICENSE
cofog-2.0.0.dist-info/WHEEL
cofog-2.0.0.dist-info/METADATA
cofog-2.0.0.dist-info/RECORD
