Metadata-Version: 2.1
Name: cofog
Version: 2.0.0
Summary: Cofog
Home-page: https://github.com/oliverjwroberts/cofog
License: MIT
Author: Oliver Roberts
Author-email: oliverjwroberts@gmail.com
Requires-Python: >=3.8,<4.0
Classifier: Development Status :: 5 - Production/Stable
Classifier: License :: OSI Approved :: MIT License
Classifier: Programming Language :: Python :: 3
Classifier: Programming Language :: Python :: 3.8
Classifier: Programming Language :: Python :: 3.9
Classifier: Programming Language :: Python :: 3.10
Requires-Dist: click (>=8.0.1)
Project-URL: Changelog, https://github.com/oliverjwroberts/cofog/releases
Project-URL: Documentation, https://cofog.readthedocs.io
Project-URL: Repository, https://github.com/oliverjwroberts/cofog
